[
    {
        "pleietrengende": {
            "identitetsnummer": "27870899799",
            "fødselsdato": "2008-07-27",
            "aktørId": "2175638020356",
            "fornavn": "RAVGUL",
            "mellomnavn": null,
            "etternavn": "LØVETANN"
        },
        "sak": {
            "saksnummer": "1DQAQRW",
            "utledetStatus": {
                "status": "UNDER_BEHANDLING",
                "aksjonspunkter": [{ "venteårsak": "FOR_TIDLIG_SOKNAD", "tidsfrist": "2024-05-26T22:00:00.000Z" }],
                "saksbehandlingsFrist": "2024-02-13T07:52:43.049Z"
            },
            "saksbehandlingsFrist": null,
            "fagsakYtelseType": { "kode": "PSB", "kodeverk": "FAGSAK_YTELSE" },
            "ytelseType": "PSB",
            "behandlinger": [
                {
                    "status": "UNDER_BEHANDLING",
                    "opprettetTidspunkt": "2024-02-13T07:53:56.000Z",
                    "avsluttetTidspunkt": null,
                    "innsendelser": [
                        {
                            "søknadId": "cb528acf-d452-4572-959d-27492e3f10ed",
                            "innsendelsestype": "UKJENT",
                            "k9FormatInnsendelse": {
                                "søknadId": "cb528acf-d452-4572-959d-27492e3f10ed",
                                "versjon": "1.0.0",
                                "mottattDato": "2024-02-13T07:52:43.049Z",
                                "søker": { "norskIdentitetsnummer": "03867198392" },
                                "språk": "nb",
                                "ytelse": {
                                    "type": "PLEIEPENGER_SYKT_BARN",
                                    "barn": { "norskIdentitetsnummer": "27870899799", "fødselsdato": null },
                                    "søknadsperiode": ["2024-02-26/2024-02-29"],
                                    "endringsperiode": [],
                                    "trekkKravPerioder": [],
                                    "opptjeningAktivitet": {},
                                    "dataBruktTilUtledning": null,
                                    "annetDataBruktTilUtledning": {
                                        "harForståttRettigheterOgPlikter": true,
                                        "harBekreftetOpplysninger": true,
                                        "soknadDialogCommitSha": null,
                                        "annetData": null
                                    },
                                    "infoFraPunsj": null,
                                    "bosteder": { "perioder": {}, "perioderSomSkalSlettes": {} },
                                    "utenlandsopphold": { "perioder": {}, "perioderSomSkalSlettes": {} },
                                    "beredskap": { "perioder": {}, "perioderSomSkalSlettes": {} },
                                    "nattevåk": { "perioder": {}, "perioderSomSkalSlettes": {} },
                                    "tilsynsordning": {
                                        "perioder": { "2024-02-26/2024-02-29": { "etablertTilsynTimerPerDag": "PT0S" } }
                                    },
                                    "lovbestemtFerie": { "perioder": {} },
                                    "arbeidstid": {
                                        "arbeidstakerList": [
                                            {
                                                "norskIdentitetsnummer": null,
                                                "organisasjonsnummer": "839942907",
                                                "organisasjonsnavn": "HÅRREISENDE FRISØR",
                                                "arbeidstidInfo": {
                                                    "perioder": {
                                                        "2024-02-26/2024-02-29": {
                                                            "jobberNormaltTimerPerDag": "PT8H",
                                                            "faktiskArbeidTimerPerDag": "PT0S"
                                                        }
                                                    }
                                                }
                                            }
                                        ],
                                        "frilanserArbeidstidInfo": {
                                            "perioder": {
                                                "2024-02-26/2024-02-29": {
                                                    "jobberNormaltTimerPerDag": "PT0S",
                                                    "faktiskArbeidTimerPerDag": "PT0S"
                                                }
                                            }
                                        },
                                        "selvstendigNæringsdrivendeArbeidstidInfo": null
                                    },
                                    "uttak": {
                                        "perioder": {
                                            "2024-02-26/2024-02-29": { "timerPleieAvBarnetPerDag": "PT7H30M" }
                                        }
                                    },
                                    "omsorg": { "relasjonTilBarnet": null, "beskrivelseAvOmsorgsrollen": null }
                                },
                                "journalposter": [],
                                "begrunnelseForInnsending": { "tekst": null },
                                "kildesystem": "søknadsdialog"
                            },
                            "dokumenter": [
                                {
                                    "journalpostId": "637581439",
                                    "dokumentInfoId": "667123743",
                                    "saksnummer": "1DQAQRW",
                                    "tittel": "Søknad om pleiepenger for sykt barn",
                                    "dokumentType": "PLEIEPENGER_SYKT_BARN_SOKNAD",
                                    "filtype": "PDF",
                                    "harTilgang": true,
                                    "url": "http://sif-innsyn-api/dokument/637581439/667123743/ARKIV",
                                    "relevanteDatoer": [
                                        { "dato": "2024-02-13T08:52:46", "datotype": "DATO_OPPRETTET" },
                                        { "dato": "2024-02-13T08:52:46", "datotype": "DATO_DOKUMENT" },
                                        { "dato": "2024-02-13T08:52:54", "datotype": "DATO_JOURNALFOERT" },
                                        { "dato": "2024-02-13T08:52:43", "datotype": "DATO_REGISTRERT" }
                                    ]
                                },
                                {
                                    "journalpostId": "637581439",
                                    "dokumentInfoId": "667123744",
                                    "saksnummer": "1DQAQRW",
                                    "tittel": "gray-tile.png",
                                    "dokumentType": "PLEIEPENGER_SYKT_BARN_SOKNAD",
                                    "filtype": "PDF",
                                    "harTilgang": true,
                                    "url": "http://sif-innsyn-api/dokument/637581439/667123744/ARKIV",
                                    "relevanteDatoer": [
                                        { "dato": "2024-02-13T08:52:46", "datotype": "DATO_OPPRETTET" },
                                        { "dato": "2024-02-13T08:52:46", "datotype": "DATO_DOKUMENT" },
                                        { "dato": "2024-02-13T08:52:54", "datotype": "DATO_JOURNALFOERT" },
                                        { "dato": "2024-02-13T08:52:43", "datotype": "DATO_REGISTRERT" }
                                    ]
                                }
                            ],
                            "arbeidsgivere": [{ "organisasjonsnummer": "839942907", "navn": "HÅRREISENDE FRISØR" }]
                        },
                        {
                            "søknadId": "1ff629d9-930c-4cc8-bb2f-ec53b1f5e9cf",
                            "innsendelsestype": "ENDRINGSMELDING",
                            "k9FormatInnsendelse": {
                                "søknadId": "1ff629d9-930c-4cc8-bb2f-ec53b1f5e9cf",
                                "versjon": "1.0.0",
                                "mottattDato": "2024-02-16T15:12:32.631Z",
                                "søker": { "norskIdentitetsnummer": "03867198392" },
                                "språk": null,
                                "ytelse": {
                                    "type": "PLEIEPENGER_SYKT_BARN",
                                    "barn": { "norskIdentitetsnummer": "27870899799", "fødselsdato": "2008-07-27" },
                                    "søknadsperiode": [],
                                    "endringsperiode": [],
                                    "trekkKravPerioder": [],
                                    "opptjeningAktivitet": {},
                                    "dataBruktTilUtledning": {
                                        "harForståttRettigheterOgPlikter": null,
                                        "harBekreftetOpplysninger": null,
                                        "samtidigHjemme": null,
                                        "harMedsøker": null,
                                        "soknadDialogCommitSha": null,
                                        "bekrefterPeriodeOver8Uker": null,
                                        "ukjenteArbeidsforhold": []
                                    },
                                    "annetDataBruktTilUtledning": {
                                        "harForståttRettigheterOgPlikter": null,
                                        "harBekreftetOpplysninger": null,
                                        "soknadDialogCommitSha": null,
                                        "annetData": "{\"valgteEndringer\":{\"arbeidstid\":true,\"lovbestemtFerie\":false}}"
                                    },
                                    "infoFraPunsj": null,
                                    "bosteder": { "perioder": {}, "perioderSomSkalSlettes": {} },
                                    "utenlandsopphold": { "perioder": {}, "perioderSomSkalSlettes": {} },
                                    "beredskap": { "perioder": {}, "perioderSomSkalSlettes": {} },
                                    "nattevåk": { "perioder": {}, "perioderSomSkalSlettes": {} },
                                    "tilsynsordning": { "perioder": {} },
                                    "lovbestemtFerie": { "perioder": {} },
                                    "arbeidstid": {
                                        "arbeidstakerList": [
                                            {
                                                "norskIdentitetsnummer": null,
                                                "organisasjonsnummer": "839942907",
                                                "organisasjonsnavn": "HÅRREISENDE FRISØR",
                                                "arbeidstidInfo": {
                                                    "perioder": {
                                                        "2024-02-26/2024-02-29": {
                                                            "jobberNormaltTimerPerDag": "PT8H",
                                                            "faktiskArbeidTimerPerDag": "PT0S"
                                                        }
                                                    }
                                                }
                                            }
                                        ],
                                        "frilanserArbeidstidInfo": null,
                                        "selvstendigNæringsdrivendeArbeidstidInfo": null
                                    },
                                    "uttak": { "perioder": {} },
                                    "omsorg": { "relasjonTilBarnet": null, "beskrivelseAvOmsorgsrollen": null }
                                },
                                "journalposter": [],
                                "begrunnelseForInnsending": { "tekst": null },
                                "kildesystem": "endringsdialog"
                            },
                            "dokumenter": [
                                {
                                    "journalpostId": "637582236",
                                    "dokumentInfoId": "667124640",
                                    "saksnummer": "1DQAQRW",
                                    "tittel": "Endringsmelding for pleiepenger sykt barn",
                                    "dokumentType": "PLEIEPENGER_SYKT_BARN_SOKNAD",
                                    "filtype": "PDF",
                                    "harTilgang": true,
                                    "url": "http://sif-innsyn-api/dokument/637582236/667124640/ARKIV",
                                    "relevanteDatoer": [
                                        { "dato": "2024-02-16T16:12:36", "datotype": "DATO_OPPRETTET" },
                                        { "dato": "2024-02-16T16:12:36", "datotype": "DATO_DOKUMENT" },
                                        { "dato": "2024-02-16T16:12:42", "datotype": "DATO_JOURNALFOERT" },
                                        { "dato": "2024-02-16T16:12:32", "datotype": "DATO_REGISTRERT" }
                                    ]
                                }
                            ],
                            "arbeidsgivere": [{ "organisasjonsnummer": "839942907", "navn": "HÅRREISENDE FRISØR" }]
                        },
                        {
                            "søknadId": "7cfe7997-cea2-4bb6-a0e1-23899fc38bda",
                            "innsendelsestype": "ENDRINGSMELDING",
                            "k9FormatInnsendelse": {
                                "søknadId": "7cfe7997-cea2-4bb6-a0e1-23899fc38bda",
                                "versjon": "1.0.0",
                                "mottattDato": "2024-02-13T07:57:22.932Z",
                                "søker": { "norskIdentitetsnummer": "03867198392" },
                                "språk": null,
                                "ytelse": {
                                    "type": "PLEIEPENGER_SYKT_BARN",
                                    "barn": { "norskIdentitetsnummer": "27870899799", "fødselsdato": "2008-07-27" },
                                    "søknadsperiode": [],
                                    "endringsperiode": [],
                                    "trekkKravPerioder": [],
                                    "opptjeningAktivitet": {},
                                    "dataBruktTilUtledning": {
                                        "harForståttRettigheterOgPlikter": null,
                                        "harBekreftetOpplysninger": null,
                                        "samtidigHjemme": null,
                                        "harMedsøker": null,
                                        "soknadDialogCommitSha": null,
                                        "bekrefterPeriodeOver8Uker": null,
                                        "ukjenteArbeidsforhold": []
                                    },
                                    "annetDataBruktTilUtledning": {
                                        "harForståttRettigheterOgPlikter": null,
                                        "harBekreftetOpplysninger": null,
                                        "soknadDialogCommitSha": null,
                                        "annetData": "{\"valgteEndringer\":{\"arbeidstid\":true,\"lovbestemtFerie\":false}}"
                                    },
                                    "infoFraPunsj": null,
                                    "bosteder": { "perioder": {}, "perioderSomSkalSlettes": {} },
                                    "utenlandsopphold": { "perioder": {}, "perioderSomSkalSlettes": {} },
                                    "beredskap": { "perioder": {}, "perioderSomSkalSlettes": {} },
                                    "nattevåk": { "perioder": {}, "perioderSomSkalSlettes": {} },
                                    "tilsynsordning": { "perioder": {} },
                                    "lovbestemtFerie": { "perioder": {} },
                                    "arbeidstid": {
                                        "arbeidstakerList": [
                                            {
                                                "norskIdentitetsnummer": null,
                                                "organisasjonsnummer": "839942907",
                                                "organisasjonsnavn": "HÅRREISENDE FRISØR",
                                                "arbeidstidInfo": {
                                                    "perioder": {
                                                        "2024-02-26/2024-02-29": {
                                                            "jobberNormaltTimerPerDag": "PT8H",
                                                            "faktiskArbeidTimerPerDag": "PT1H36M"
                                                        }
                                                    }
                                                }
                                            }
                                        ],
                                        "frilanserArbeidstidInfo": null,
                                        "selvstendigNæringsdrivendeArbeidstidInfo": null
                                    },
                                    "uttak": { "perioder": {} },
                                    "omsorg": { "relasjonTilBarnet": null, "beskrivelseAvOmsorgsrollen": null }
                                },
                                "journalposter": [],
                                "begrunnelseForInnsending": { "tekst": null },
                                "kildesystem": "endringsdialog"
                            },
                            "dokumenter": [
                                {
                                    "journalpostId": "637581441",
                                    "dokumentInfoId": "667123746",
                                    "saksnummer": "1DQAQRW",
                                    "tittel": "Endringsmelding for pleiepenger sykt barn",
                                    "dokumentType": "PLEIEPENGER_SYKT_BARN_SOKNAD",
                                    "filtype": "PDF",
                                    "harTilgang": true,
                                    "url": "http://sif-innsyn-api/dokument/637581441/667123746/ARKIV",
                                    "relevanteDatoer": [
                                        { "dato": "2024-02-13T08:57:24", "datotype": "DATO_OPPRETTET" },
                                        { "dato": "2024-02-13T08:57:24", "datotype": "DATO_DOKUMENT" },
                                        { "dato": "2024-02-13T08:57:30", "datotype": "DATO_JOURNALFOERT" },
                                        { "dato": "2024-02-13T08:57:22", "datotype": "DATO_REGISTRERT" }
                                    ]
                                }
                            ],
                            "arbeidsgivere": [{ "organisasjonsnummer": "839942907", "navn": "HÅRREISENDE FRISØR" }]
                        },
                        {
                            "søknadId": "af5088f4-7739-4c47-8665-ee1397200e8f",
                            "innsendelsestype": "ENDRINGSMELDING",
                            "k9FormatInnsendelse": {
                                "søknadId": "af5088f4-7739-4c47-8665-ee1397200e8f",
                                "versjon": "1.0.0",
                                "mottattDato": "2024-02-14T11:59:40.061Z",
                                "søker": { "norskIdentitetsnummer": "03867198392" },
                                "språk": null,
                                "ytelse": {
                                    "type": "PLEIEPENGER_SYKT_BARN",
                                    "barn": { "norskIdentitetsnummer": "27870899799", "fødselsdato": "2008-07-27" },
                                    "søknadsperiode": [],
                                    "endringsperiode": [],
                                    "trekkKravPerioder": [],
                                    "opptjeningAktivitet": {},
                                    "dataBruktTilUtledning": {
                                        "harForståttRettigheterOgPlikter": null,
                                        "harBekreftetOpplysninger": null,
                                        "samtidigHjemme": null,
                                        "harMedsøker": null,
                                        "soknadDialogCommitSha": null,
                                        "bekrefterPeriodeOver8Uker": null,
                                        "ukjenteArbeidsforhold": []
                                    },
                                    "annetDataBruktTilUtledning": {
                                        "harForståttRettigheterOgPlikter": null,
                                        "harBekreftetOpplysninger": null,
                                        "soknadDialogCommitSha": null,
                                        "annetData": "{\"valgteEndringer\":{\"arbeidstid\":true,\"lovbestemtFerie\":false}}"
                                    },
                                    "infoFraPunsj": null,
                                    "bosteder": { "perioder": {}, "perioderSomSkalSlettes": {} },
                                    "utenlandsopphold": { "perioder": {}, "perioderSomSkalSlettes": {} },
                                    "beredskap": { "perioder": {}, "perioderSomSkalSlettes": {} },
                                    "nattevåk": { "perioder": {}, "perioderSomSkalSlettes": {} },
                                    "tilsynsordning": { "perioder": {} },
                                    "lovbestemtFerie": { "perioder": {} },
                                    "arbeidstid": {
                                        "arbeidstakerList": [
                                            {
                                                "norskIdentitetsnummer": null,
                                                "organisasjonsnummer": "839942907",
                                                "organisasjonsnavn": "HÅRREISENDE FRISØR",
                                                "arbeidstidInfo": {
                                                    "perioder": {
                                                        "2024-02-26/2024-02-29": {
                                                            "jobberNormaltTimerPerDag": "PT8H",
                                                            "faktiskArbeidTimerPerDag": "PT48M"
                                                        }
                                                    }
                                                }
                                            }
                                        ],
                                        "frilanserArbeidstidInfo": null,
                                        "selvstendigNæringsdrivendeArbeidstidInfo": null
                                    },
                                    "uttak": { "perioder": {} },
                                    "omsorg": { "relasjonTilBarnet": null, "beskrivelseAvOmsorgsrollen": null }
                                },
                                "journalposter": [],
                                "begrunnelseForInnsending": { "tekst": null },
                                "kildesystem": "endringsdialog"
                            },
                            "dokumenter": [
                                {
                                    "journalpostId": "637581723",
                                    "dokumentInfoId": "667124045",
                                    "saksnummer": "1DQAQRW",
                                    "tittel": "Endringsmelding for pleiepenger sykt barn",
                                    "dokumentType": "PLEIEPENGER_SYKT_BARN_SOKNAD",
                                    "filtype": "PDF",
                                    "harTilgang": true,
                                    "url": "http://sif-innsyn-api/dokument/637581723/667124045/ARKIV",
                                    "relevanteDatoer": [
                                        { "dato": "2024-02-14T12:59:43", "datotype": "DATO_OPPRETTET" },
                                        { "dato": "2024-02-14T12:59:43", "datotype": "DATO_DOKUMENT" },
                                        { "dato": "2024-02-14T12:59:50", "datotype": "DATO_JOURNALFOERT" },
                                        { "dato": "2024-02-14T12:59:40", "datotype": "DATO_REGISTRERT" }
                                    ]
                                }
                            ],
                            "arbeidsgivere": [{ "organisasjonsnummer": "839942907", "navn": "HÅRREISENDE FRISØR" }]
                        },
                        {
                            "søknadId": "1027d623-e249-4f97-888b-6f9b35ce59ea",
                            "innsendelsestype": "SØKNAD",
                            "k9FormatInnsendelse": {
                                "søknadId": "1027d623-e249-4f97-888b-6f9b35ce59ea",
                                "versjon": "1.0.0",
                                "mottattDato": "2024-03-18T10:27:23.907Z",
                                "søker": { "norskIdentitetsnummer": "03867198392" },
                                "språk": "nb",
                                "ytelse": {
                                    "type": "PLEIEPENGER_SYKT_BARN",
                                    "barn": { "norskIdentitetsnummer": "27870899799", "fødselsdato": null },
                                    "søknadsperiode": ["2024-03-27/2024-03-30"],
                                    "endringsperiode": [],
                                    "trekkKravPerioder": [],
                                    "opptjeningAktivitet": {},
                                    "dataBruktTilUtledning": null,
                                    "annetDataBruktTilUtledning": {
                                        "harForståttRettigheterOgPlikter": true,
                                        "harBekreftetOpplysninger": true,
                                        "soknadDialogCommitSha": null,
                                        "annetData": null
                                    },
                                    "infoFraPunsj": null,
                                    "bosteder": { "perioder": {}, "perioderSomSkalSlettes": {} },
                                    "utenlandsopphold": { "perioder": {}, "perioderSomSkalSlettes": {} },
                                    "beredskap": { "perioder": {}, "perioderSomSkalSlettes": {} },
                                    "nattevåk": { "perioder": {}, "perioderSomSkalSlettes": {} },
                                    "tilsynsordning": {
                                        "perioder": { "2024-03-27/2024-03-30": { "etablertTilsynTimerPerDag": "PT0S" } }
                                    },
                                    "lovbestemtFerie": { "perioder": {} },
                                    "arbeidstid": {
                                        "arbeidstakerList": [
                                            {
                                                "norskIdentitetsnummer": null,
                                                "organisasjonsnummer": "839942907",
                                                "organisasjonsnavn": "HÅRREISENDE FRISØR",
                                                "arbeidstidInfo": {
                                                    "perioder": {
                                                        "2024-03-27/2024-03-30": {
                                                            "jobberNormaltTimerPerDag": "PT4H",
                                                            "faktiskArbeidTimerPerDag": "PT0S"
                                                        }
                                                    }
                                                }
                                            }
                                        ],
                                        "frilanserArbeidstidInfo": {
                                            "perioder": {
                                                "2024-03-27/2024-03-30": {
                                                    "jobberNormaltTimerPerDag": "PT0S",
                                                    "faktiskArbeidTimerPerDag": "PT0S"
                                                }
                                            }
                                        },
                                        "selvstendigNæringsdrivendeArbeidstidInfo": null
                                    },
                                    "uttak": {
                                        "perioder": {
                                            "2024-03-27/2024-03-30": { "timerPleieAvBarnetPerDag": "PT7H30M" }
                                        }
                                    },
                                    "omsorg": { "relasjonTilBarnet": null, "beskrivelseAvOmsorgsrollen": null }
                                },
                                "journalposter": [],
                                "begrunnelseForInnsending": { "tekst": null },
                                "kildesystem": "søknadsdialog"
                            },
                            "dokumenter": [
                                {
                                    "journalpostId": "637595058",
                                    "dokumentInfoId": "667141374",
                                    "saksnummer": "1DQAQRW",
                                    "tittel": "Søknad om pleiepenger for sykt barn",
                                    "dokumentType": "PLEIEPENGER_SYKT_BARN_SOKNAD",
                                    "filtype": "PDF",
                                    "harTilgang": true,
                                    "url": "http://sif-innsyn-api/dokument/637595058/667141374/ARKIV",
                                    "relevanteDatoer": [
                                        { "dato": "2024-03-18T11:27:28", "datotype": "DATO_OPPRETTET" },
                                        { "dato": "2024-03-18T11:27:28", "datotype": "DATO_DOKUMENT" },
                                        { "dato": "2024-03-18T11:27:35", "datotype": "DATO_JOURNALFOERT" },
                                        { "dato": "2024-03-18T11:27:23", "datotype": "DATO_REGISTRERT" }
                                    ]
                                },
                                {
                                    "journalpostId": "637595058",
                                    "dokumentInfoId": "667141375",
                                    "saksnummer": "1DQAQRW",
                                    "tittel": "image (21).png",
                                    "dokumentType": "PLEIEPENGER_SYKT_BARN_SOKNAD",
                                    "filtype": "PDF",
                                    "harTilgang": true,
                                    "url": "http://sif-innsyn-api/dokument/637595058/667141375/ARKIV",
                                    "relevanteDatoer": [
                                        { "dato": "2024-03-18T11:27:28", "datotype": "DATO_OPPRETTET" },
                                        { "dato": "2024-03-18T11:27:28", "datotype": "DATO_DOKUMENT" },
                                        { "dato": "2024-03-18T11:27:35", "datotype": "DATO_JOURNALFOERT" },
                                        { "dato": "2024-03-18T11:27:23", "datotype": "DATO_REGISTRERT" }
                                    ]
                                }
                            ],
                            "arbeidsgivere": [{ "organisasjonsnummer": "839942907", "navn": "HÅRREISENDE FRISØR" }]
                        },
                        {
                            "søknadId": "84cfcf3e-069a-4d4a-9292-61a179eb2427",
                            "innsendelsestype": "SØKNAD",
                            "k9FormatInnsendelse": {
                                "søknadId": "84cfcf3e-069a-4d4a-9292-61a179eb2427",
                                "versjon": "1.0.0",
                                "mottattDato": "2024-02-15T07:45:36.078Z",
                                "søker": { "norskIdentitetsnummer": "03867198392" },
                                "språk": "nb",
                                "ytelse": {
                                    "type": "PLEIEPENGER_SYKT_BARN",
                                    "barn": { "norskIdentitetsnummer": "27870899799", "fødselsdato": null },
                                    "søknadsperiode": ["2024-03-25/2024-05-31"],
                                    "endringsperiode": [],
                                    "trekkKravPerioder": [],
                                    "opptjeningAktivitet": {},
                                    "dataBruktTilUtledning": null,
                                    "annetDataBruktTilUtledning": {
                                        "harForståttRettigheterOgPlikter": true,
                                        "harBekreftetOpplysninger": true,
                                        "soknadDialogCommitSha": null,
                                        "annetData": null
                                    },
                                    "infoFraPunsj": null,
                                    "bosteder": { "perioder": {}, "perioderSomSkalSlettes": {} },
                                    "utenlandsopphold": { "perioder": {}, "perioderSomSkalSlettes": {} },
                                    "beredskap": { "perioder": {}, "perioderSomSkalSlettes": {} },
                                    "nattevåk": { "perioder": {}, "perioderSomSkalSlettes": {} },
                                    "tilsynsordning": {
                                        "perioder": { "2024-03-25/2024-05-31": { "etablertTilsynTimerPerDag": "PT0S" } }
                                    },
                                    "lovbestemtFerie": { "perioder": {} },
                                    "arbeidstid": {
                                        "arbeidstakerList": [
                                            {
                                                "norskIdentitetsnummer": null,
                                                "organisasjonsnummer": "839942907",
                                                "organisasjonsnavn": "HÅRREISENDE FRISØR",
                                                "arbeidstidInfo": {
                                                    "perioder": {
                                                        "2024-03-25/2024-05-31": {
                                                            "jobberNormaltTimerPerDag": "PT7H30M",
                                                            "faktiskArbeidTimerPerDag": "PT0S"
                                                        }
                                                    }
                                                }
                                            }
                                        ],
                                        "frilanserArbeidstidInfo": {
                                            "perioder": {
                                                "2024-03-25/2024-05-31": {
                                                    "jobberNormaltTimerPerDag": "PT0S",
                                                    "faktiskArbeidTimerPerDag": "PT0S"
                                                }
                                            }
                                        },
                                        "selvstendigNæringsdrivendeArbeidstidInfo": null
                                    },
                                    "uttak": {
                                        "perioder": {
                                            "2024-03-25/2024-05-31": { "timerPleieAvBarnetPerDag": "PT7H30M" }
                                        }
                                    },
                                    "omsorg": { "relasjonTilBarnet": null, "beskrivelseAvOmsorgsrollen": null }
                                },
                                "journalposter": [],
                                "begrunnelseForInnsending": { "tekst": null },
                                "kildesystem": "søknadsdialog"
                            },
                            "dokumenter": [
                                {
                                    "journalpostId": "637581829",
                                    "dokumentInfoId": "667124163",
                                    "saksnummer": "1DQAQRW",
                                    "tittel": "Søknad om pleiepenger for sykt barn",
                                    "dokumentType": "PLEIEPENGER_SYKT_BARN_SOKNAD",
                                    "filtype": "PDF",
                                    "harTilgang": true,
                                    "url": "http://sif-innsyn-api/dokument/637581829/667124163/ARKIV",
                                    "relevanteDatoer": [
                                        { "dato": "2024-02-15T08:45:41", "datotype": "DATO_OPPRETTET" },
                                        { "dato": "2024-02-15T08:45:41", "datotype": "DATO_DOKUMENT" },
                                        { "dato": "2024-02-15T08:45:48", "datotype": "DATO_JOURNALFOERT" },
                                        { "dato": "2024-02-15T08:45:36", "datotype": "DATO_REGISTRERT" }
                                    ]
                                },
                                {
                                    "journalpostId": "637581829",
                                    "dokumentInfoId": "667124164",
                                    "saksnummer": "1DQAQRW",
                                    "tittel": "pc-robot 3.jpg",
                                    "dokumentType": "PLEIEPENGER_SYKT_BARN_SOKNAD",
                                    "filtype": "PDF",
                                    "harTilgang": true,
                                    "url": "http://sif-innsyn-api/dokument/637581829/667124164/ARKIV",
                                    "relevanteDatoer": [
                                        { "dato": "2024-02-15T08:45:41", "datotype": "DATO_OPPRETTET" },
                                        { "dato": "2024-02-15T08:45:41", "datotype": "DATO_DOKUMENT" },
                                        { "dato": "2024-02-15T08:45:48", "datotype": "DATO_JOURNALFOERT" },
                                        { "dato": "2024-02-15T08:45:36", "datotype": "DATO_REGISTRERT" }
                                    ]
                                }
                            ],
                            "arbeidsgivere": [{ "organisasjonsnummer": "839942907", "navn": "HÅRREISENDE FRISØR" }]
                        },
                        {
                            "søknadId": "9aaee6b4-0218-4a3b-a56a-1164c0fb7f75",
                            "innsendelsestype": "ENDRINGSMELDING",
                            "k9FormatInnsendelse": {
                                "søknadId": "9aaee6b4-0218-4a3b-a56a-1164c0fb7f75",
                                "versjon": "1.0.0",
                                "mottattDato": "2024-02-13T07:56:25.433Z",
                                "søker": { "norskIdentitetsnummer": "03867198392" },
                                "språk": null,
                                "ytelse": {
                                    "type": "PLEIEPENGER_SYKT_BARN",
                                    "barn": { "norskIdentitetsnummer": "27870899799", "fødselsdato": "2008-07-27" },
                                    "søknadsperiode": [],
                                    "endringsperiode": [],
                                    "trekkKravPerioder": [],
                                    "opptjeningAktivitet": {},
                                    "dataBruktTilUtledning": {
                                        "harForståttRettigheterOgPlikter": null,
                                        "harBekreftetOpplysninger": null,
                                        "samtidigHjemme": null,
                                        "harMedsøker": null,
                                        "soknadDialogCommitSha": null,
                                        "bekrefterPeriodeOver8Uker": null,
                                        "ukjenteArbeidsforhold": []
                                    },
                                    "annetDataBruktTilUtledning": {
                                        "harForståttRettigheterOgPlikter": null,
                                        "harBekreftetOpplysninger": null,
                                        "soknadDialogCommitSha": null,
                                        "annetData": "{\"valgteEndringer\":{\"arbeidstid\":false,\"lovbestemtFerie\":true}}"
                                    },
                                    "infoFraPunsj": null,
                                    "bosteder": { "perioder": {}, "perioderSomSkalSlettes": {} },
                                    "utenlandsopphold": { "perioder": {}, "perioderSomSkalSlettes": {} },
                                    "beredskap": { "perioder": {}, "perioderSomSkalSlettes": {} },
                                    "nattevåk": { "perioder": {}, "perioderSomSkalSlettes": {} },
                                    "tilsynsordning": { "perioder": {} },
                                    "lovbestemtFerie": {
                                        "perioder": { "2024-02-27/2024-02-28": { "skalHaFerie": true } }
                                    },
                                    "arbeidstid": {
                                        "arbeidstakerList": [],
                                        "frilanserArbeidstidInfo": null,
                                        "selvstendigNæringsdrivendeArbeidstidInfo": null
                                    },
                                    "uttak": { "perioder": {} },
                                    "omsorg": { "relasjonTilBarnet": null, "beskrivelseAvOmsorgsrollen": null }
                                },
                                "journalposter": [],
                                "begrunnelseForInnsending": { "tekst": null },
                                "kildesystem": "endringsdialog"
                            },
                            "dokumenter": [
                                {
                                    "journalpostId": "637581440",
                                    "dokumentInfoId": "667123745",
                                    "saksnummer": "1DQAQRW",
                                    "tittel": "Endringsmelding for pleiepenger sykt barn",
                                    "dokumentType": "PLEIEPENGER_SYKT_BARN_SOKNAD",
                                    "filtype": "PDF",
                                    "harTilgang": true,
                                    "url": "http://sif-innsyn-api/dokument/637581440/667123745/ARKIV",
                                    "relevanteDatoer": [
                                        { "dato": "2024-02-13T08:56:40", "datotype": "DATO_OPPRETTET" },
                                        { "dato": "2024-02-13T08:56:40", "datotype": "DATO_DOKUMENT" },
                                        { "dato": "2024-02-13T08:56:45", "datotype": "DATO_JOURNALFOERT" },
                                        { "dato": "2024-02-13T08:56:25", "datotype": "DATO_REGISTRERT" }
                                    ]
                                }
                            ],
                            "arbeidsgivere": []
                        }
                    ],
                    "aksjonspunkter": [],
                    "utgåendeDokumenter": []
                }
            ]
        }
    }
]
